src/__init__.py
src/__main__.py
src/main.py
src/common/__init__.py
src/common/config.py
src/common/const.py
src/common/server.py
src/tools/__init__.py
src/tools/authentication_management_tools.py
src/tools/client_tools.py
src/tools/group_tools.py
src/tools/keycloak_client.py
src/tools/realm_tools.py
src/tools/role_tools.py
src/tools/user_tools.py
mcp_keycloak/__init__.py
mcp_keycloak/__main__.py
mcp_keycloak/main.py
mcp_keycloak/common/__init__.py
mcp_keycloak/common/config.py
mcp_keycloak/common/const.py
mcp_keycloak/common/server.py
mcp_keycloak/tools/__init__.py
mcp_keycloak/tools/authentication_management_tools.py
mcp_keycloak/tools/client_tools.py
mcp_keycloak/tools/group_tools.py
mcp_keycloak/tools/keycloak_client.py
mcp_keycloak/tools/realm_tools.py
mcp_keycloak/tools/role_tools.py
mcp_keycloak/tools/user_tools.py
mcp_keycloak-1.2.2.dist-info/METADATA
mcp_keycloak-1.2.2.dist-info/WHEEL
mcp_keycloak-1.2.2.dist-info/entry_points.txt
mcp_keycloak-1.2.2.dist-info/licenses/LICENSE
mcp_keycloak-1.2.2.dist-info/RECORD
