Metadata-Version: 2.4
Name: mcp-keycloak
Version: 1.2.2
Summary: MCP server for Keycloak administration
License-File: LICENSE
Requires-Python: >=3.12
Requires-Dist: httpx>=0.28.1
Requires-Dist: mcp[cli]>=1.12.3
Requires-Dist: python-dotenv>=1.0.0
Requires-Dist: starlette>=0.27.0
Requires-Dist: uvicorn>=0.24.0
